aijson_utils/__init__.py
aijson_utils/actions/__init__.py
aijson_utils/actions/extract_list.py
aijson_utils/actions/extract_urls.py
aijson_utils/actions/extract_xml_tag.py
aijson_utils/actions/get_url.py
aijson_utils/tests/__init__.py
aijson_utils/tests/conftest.py
aijson_utils/tests/test_extract_urls.py
aijson_utils/tests/test_extract_xml_tag.py
aijson_utils/tests/test_get_url.py
aijson_utils-0.1.5.dist-info/LICENSE
aijson_utils-0.1.5.dist-info/METADATA
aijson_utils-0.1.5.dist-info/WHEEL
aijson_utils-0.1.5.dist-info/entry_points.txt
aijson_utils-0.1.5.dist-info/RECORD
