Metadata-Version: 2.1
Name: aijson-utils
Version: 0.1.5
Summary: AI JSON Utilities
License: MIT
Author: Rafael Irgolic
Author-email: hello@irgolic.com
Requires-Python: >=3.10,<3.13
Classifier: License :: OSI Approved :: MIT License
Classifier: Programming Language :: Python :: 3
Classifier: Programming Language :: Python :: 3.10
Classifier: Programming Language :: Python :: 3.11
Classifier: Programming Language :: Python :: 3.12
Requires-Dist: aijson-core (>=0.2.0,<0.3.0)
Requires-Dist: beautifulsoup4 (>=4.12.3,<5.0.0)
Requires-Dist: markdown (>=3.7,<4.0)
